odoo/addons/web_widget_datepicker_fulloptions/README.rst
odoo/addons/web_widget_datepicker_fulloptions/__init__.py
odoo/addons/web_widget_datepicker_fulloptions/__manifest__.py
odoo/addons/web_widget_datepicker_fulloptions/i18n/pt_BR.po
odoo/addons/web_widget_datepicker_fulloptions/i18n/web_widget_datepicker_fulloptions.pot
odoo/addons/web_widget_datepicker_fulloptions/readme/CONTRIBUTORS.rst
odoo/addons/web_widget_datepicker_fulloptions/readme/DESCRIPTION.rst
odoo/addons/web_widget_datepicker_fulloptions/static/description/change.png
odoo/addons/web_widget_datepicker_fulloptions/static/description/icon.png
odoo/addons/web_widget_datepicker_fulloptions/static/description/index.html
odoo/addons/web_widget_datepicker_fulloptions/static/src/js/web_widget_datepicker_fulloptions.js
odoo/addons/web_widget_datepicker_fulloptions/views/web_widget_datepicker_fulloptions_assets.xml
odoo14_addon_web_widget_datepicker_fulloptions-14.0.1.0.1.dev4.dist-info/METADATA
odoo14_addon_web_widget_datepicker_fulloptions-14.0.1.0.1.dev4.dist-info/WHEEL
odoo14_addon_web_widget_datepicker_fulloptions-14.0.1.0.1.dev4.dist-info/top_level.txt
odoo14_addon_web_widget_datepicker_fulloptions-14.0.1.0.1.dev4.dist-info/RECORD
